win32_setctime.py
win32_setctime-1.1.0.dist-info/LICENSE
win32_setctime-1.1.0.dist-info/METADATA
win32_setctime-1.1.0.dist-info/WHEEL
win32_setctime-1.1.0.dist-info/top_level.txt
win32_setctime-1.1.0.dist-info/RECORD
