Metadata-Version: 2.1
Name: win32-setctime
Version: 1.1.0
Summary: A small Python utility to set file creation time on Windows
Home-page: https://github.com/Delgan/win32-setctime
Author: Delgan
Author-email: delgan.py@gmail.com
License: MIT license
Download-URL: https://github.com/Delgan/win32-setctime/archive/1.1.0.tar.gz
Keywords: win32,windows,filesystem,filetime
Platform: UNKNOWN
Classifier: Development Status :: 5 - Production/Stable
Classifier: Topic :: System :: Filesystems
Classifier: Intended Audience :: Developers
Classifier: Environment :: Win32 (MS Windows)
Classifier: Natural Language :: English
Classifier: License :: OSI Approved :: MIT License
Classifier: Operating System :: Microsoft
Classifier: Programming Language :: Python
Classifier: Programming Language :: Python :: 3
Classifier: Programming Language :: Python :: 3.5
Classifier: Programming Language :: Python :: 3.6
Classifier: Programming Language :: Python :: 3.7
Classifier: Programming Language :: Python :: 3.8
Classifier: Programming Language :: Python :: 3.9
Classifier: Programming Language :: Python :: 3.10
Classifier: Programming Language :: Python :: 3 :: Only
Classifier: Programming Language :: Python :: Implementation :: CPython
Requires-Python: >=3.5
Provides-Extra: dev
License-File: LICENSE
